whisper_ui/__init__.py
whisper_ui/__main__.py
whisper_ui/handle_prefs.py
whisper_ui/install_torch.py
whisper_ui/textgrid_utils.py
whisper_ui/ui.py
whisper_ui/user_prefs.json
whisper_ui/whisper_funcs.py
whisper_ui-1.3.5.dist-info/licenses/LICENSE
whisper_ui-1.3.5.dist-info/WHEEL
whisper_ui-1.3.5.dist-info/METADATA
whisper_ui-1.3.5.dist-info/RECORD
