Metadata-Version: 2.4
Name: whisper_ui
Version: 1.3.5
Summary: A GUI for OpenAI's Whisper.
Author-email: Dan DeGenaro <drd92@georgetown.edu>
Requires-Python: >=3.8
Classifier: Programming Language :: Python :: 3
Classifier: License :: OSI Approved :: MIT License
Classifier: Operating System :: OS Independent
License-File: LICENSE
Requires-Dist: certifi
Requires-Dist: openai-whisper
Requires-Dist: tkinterdnd2
Requires-Dist: faster-whisper
Project-URL: Homepage, https://github.com/dan-the-meme-man/whisper-ui
Project-URL: Issues, https://github.com/dan-the-meme-man/whisper-ui/issues
